{"assets/images/addTemaButton.png":["assets/images/addTemaButton.png"],"assets/images/alfabeto.png":["assets/images/alfabeto.png"],"assets/images/animais.png":["assets/images/animais.png"],"assets/images/back.png":["assets/images/back.png"],"assets/images/brinquedos.png":["assets/images/brinquedos.png"],"assets/images/cancel.png":["assets/images/cancel.png"],"assets/images/configButton.png":["assets/images/configButton.png"],"assets/images/consoantes.png":["assets/images/consoantes.png"],"assets/images/cores.png":["assets/images/cores.png"],"assets/images/corpo.png":["assets/images/corpo.png"],"assets/images/falar.png":["assets/images/falar.png"],"assets/images/frutas.png":["assets/images/frutas.png"],"assets/images/homeButton.png":["assets/images/homeButton.png"],"assets/images/infoButton.png":["assets/images/infoButton.png"],"assets/images/keyboard.png":["assets/images/keyboard.png"],"assets/images/logo.png":["assets/images/logo.png"],"assets/images/objetos.png":["assets/images/objetos.png"],"assets/images/paises.png":["assets/images/paises.png"],"assets/images/playButton.png":["assets/images/playButton.png"],"assets/images/televis%C3%A3o.png":["assets/images/televis%C3%A3o.png"],"assets/images/tv.png":["assets/images/tv.png"],"assets/images/vogais.png":["assets/images/vogais.png"],"assets/images/vogaisKeyboard.png":["assets/images/vogaisKeyboard.png"],"packages/cupertino_icons/assets/CupertinoIcons.ttf":["packages/cupertino_icons/assets/CupertinoIcons.ttf"]}